tinymesh_yr-1.0.0.dist-info/METADATA
tinymesh_yr-1.0.0.dist-info/RECORD
tinymesh_yr-1.0.0.dist-info/WHEEL
tinymesh_yr-1.0.0.dist-info/top_level.txt
yr/__init__.py
yr/yr.py
