Metadata-Version: 2.1
Name: tinymesh-yr
Version: 1.0.0
Summary: Python app to retrieve YR weather temperature and precipitation
Home-page: https://github.com/vicinityh2020/tinymesh-yr-module
Author: German Poljakov
Author-email: german@tiny-mesh.com
License: MIT
Platform: UNKNOWN
Requires-Dist: requests
